terminal_dungeon/__init__.py
terminal_dungeon/__main__.py
terminal_dungeon/camera.py
terminal_dungeon/engine.py
terminal_dungeon/raycaster.py
terminal_dungeon/read_assets.py
terminal_dungeon-0.1.2.dist-info/LICENSE
terminal_dungeon-0.1.2.dist-info/METADATA
terminal_dungeon-0.1.2.dist-info/WHEEL
terminal_dungeon-0.1.2.dist-info/top_level.txt
terminal_dungeon-0.1.2.dist-info/RECORD
