Metadata-Version: 2.1
Name: terminal_dungeon
Version: 0.1.2
Summary: A raycasting library for your terminal!
Author-email: salt-die <salt-die@protonmail.com>
License: MIT
Project-URL: repository, https://github.com/salt-die/terminal_dungeon
Classifier: Programming Language :: Python :: 3
Classifier: License :: OSI Approved :: MIT License
Classifier: Operating System :: OS Independent
Requires-Python: >=3.10
License-File: LICENSE
Requires-Dist: numpy >=1.26.4
Requires-Dist: pynput >=1.7.5
Requires-Dist: windows-curses >=2.3.2 ; platform_system == "Windows"
